dataverk_publisher/__init__.py
dataverk_publisher/connectors/__init__.py
dataverk_publisher/connectors/elastic.py
dataverk_publisher/connectors/resources/__init__.py
dataverk_publisher/connectors/resources/base.py
dataverk_publisher/connectors/resources/dakan.py
dataverk_publisher/connectors/resources/google.py
dataverk_publisher/connectors/resources/local.py
dataverk_publisher/elastic_writer.py
dataverk_publisher/publish.py
dataverk_publisher/storage_writer.py
dataverk_publisher/utils/__init__.py
dataverk_publisher/utils/environment.py
dataverk_publisher/utils/file_functions.py
dataverk_publisher/utils/logger.py
dataverk_publisher-0.0.8.dist-info/WHEEL
dataverk_publisher-0.0.8.dist-info/METADATA
dataverk_publisher-0.0.8.dist-info/RECORD
