Metadata-Version: 2.1
Name: dataverk-publisher
Version: 0.0.8
Summary: 
Author: erikvatt
Author-email: erik.vattekar@nav.no
Requires-Python: >=3.6.8,<4.0.0
Classifier: Programming Language :: Python :: 3
Classifier: Programming Language :: Python :: 3.10
Classifier: Programming Language :: Python :: 3.7
Classifier: Programming Language :: Python :: 3.8
Classifier: Programming Language :: Python :: 3.9
Requires-Dist: deetly (>=0.0.26,<0.0.27)
Requires-Dist: google-cloud-storage (>=1.40.0,<2.0.0)
Requires-Dist: requests (>=2.24.0,<3.0.0)
